Workbook

Sheet Project Tracking
A1: Total Project Tracking_TEAM_5
A2: Travel Attraction Ticket Booking Platform | Information in columns A-E is initialized from project_tracking.docx; columns F-J are used by the team to manage progress at the end of each SWP development iteration.
A3: # | B3: Screen/Function | C3: Feature | D3: Actor | E3: Screen/Function Description | F3: In Charge | G3: Status | H3: Actual | I3: Updated | J3: Update Details
A4: 1 | B4: Register Screen | C4: Authentication and Profile Management | D4: Guest | E4: This screen allows Guests to register a new account by entering required information such as full name, email, phone number, and password. It supports the Register Account use case. | F4: Như | G4: To Do | H4: iter1 | I4: none | J4: Initial SWP plan: build UI, validation, authentication API, role-based access control, database mapping, and unit/integration tests.
A5: 2 | B5: Email Verification Screen | C5: Authentication and Profile Management | D5: Guest, Notification Service | E5: This screen allows Guests to verify their account by entering the verification code sent by the Notification Service. It supports the Send Verification Code use case. | F5: Như | G5: To Do | H5: iter1 | I5: none | J5: Initial SWP plan: build UI, validation, authentication API, role-based access control, database mapping, and unit/integration tests.
A6: 3 | B6: Sign in Screen | C6: Authentication and Profile Management | D6: Guest, Customer, Attraction Partner, Admin | E6: This screen allows Guests, Customers, Attraction Partners, and Admins to log in to the system using valid credentials. It supports the Login use case. | F6: Trần Hoàng Anh | G6: To Do | H6: iter1 | I6: none | J6: Initial SWP plan: build UI, validation, authentication API, role-based access control, database mapping, and unit/integration tests.
A7: 4 | B7: Google Sign in Screen | C7: Authentication and Profile Management | D7: Guest, Customer, Google Authentication Service | E7: This screen allows Guests or Customers to sign in using a Google account through Google Authentication Service. It supports the Login with Google use case. | F7: Phú | G7: To Do | H7: iter1 | I7: none | J7: Initial SWP plan: build UI, validation, authentication API, role-based access control, database mapping, and unit/integration tests.
A8: 5 | B8: Forgot Password Screen | C8: Authentication and Profile Management | D8: Guest, Customer, Attraction Partner, Admin, Notification Service | E8: This screen allows users to request a password reset link or verification code when they cannot remember their password. It supports the Forgot Password use case. | F8: Như | G8: To Do | H8: iter1 | I8: none | J8: Initial SWP plan: build UI, validation, authentication API, role-based access control, database mapping, and unit/integration tests.
A9: 6 | B9: Reset Password Screen | C9: Authentication and Profile Management | D9: Guest, Customer, Attraction Partner, Admin | E9: This screen allows users to create a new password after verifying the reset request. It supports the Reset Password use case. | F9: Như | G9: To Do | H9: iter1 | I9: none | J9: Initial SWP plan: build UI, validation, authentication API, role-based access control, database mapping, and unit/integration tests.
A10: 7 | B10: Customer Profile Update Screen | C10: Authentication and Profile Management | D10: Customer | E10: This screen allows Customers to update personal profile information such as name, phone number, email, and avatar. It supports the Update Profile use case. | F10: Trần Hoàng Anh | G10: To Do | H10: iter1 | I10: none | J10: Initial SWP plan: build UI, validation, authentication API, role-based access control, database mapping, and unit/integration tests.
A11: 8 | B11: Partner Profile Update Screen | C11: Authentication and Profile Management | D11: Attraction Partner | E11: This screen allows Attraction Partners to update business profile information such as business name, contact information, address, and business documents. It supports the Update Partner Profile use case. | F11: Lộc | G11: To Do | H11: iter1 | I11: none | J11: Initial SWP plan: build UI, validation, authentication API, role-based access control, database mapping, and unit/integration tests.
A12: 9 | B12: User Management Screen | C12: Authentication and Profile Management | D12: Admin | E12: This screen allows Admins to view the user list and lock or unlock user accounts when necessary. It supports View User List and Lock or Unlock User Account. | F12: Trần Hoàng Anh | G12: To Do | H12: iter1 | I12: none | J12: Initial SWP plan: build UI, validation, authentication API, role-based access control, database mapping, and unit/integration tests.
A13: 10 | B13: Partner Account Management Screen | C13: Authentication and Profile Management | D13: Admin, Attraction Partner, Notification Service | E13: This screen allows Admins to lock or unlock Attraction Partner accounts and send account status notifications. It supports Lock or Unlock Partner Account and Send Account Status Notification. | F13: Trần Hoàng Anh | G13: To Do | H13: iter1 | I13: none | J13: Initial SWP plan: build UI, validation, authentication API, role-based access control, database mapping, and unit/integration tests.
A14: 11 | B14: Attraction Search Screen | C14: Attraction and Ticket Product Management | D14: Guest, Customer | E14: This screen allows Guests and Customers to search and filter attractions by name, location, category, price, or rating. It supports the Search and Filter Attractions use case. | F14: Lộc | G14: To Do | H14: iter2 | I14: none | J14: Initial SWP plan: build listing/search/product workflows, approval status handling, database CRUD, and acceptance tests.
A15: 12 | B15: Attraction Detail Screen | C15: Attraction and Ticket Product Management | D15: Guest, Customer | E15: This screen allows Guests and Customers to view detailed information about an attraction, including description, images, price, location, opening time, and related ticket products. It supports View Attraction Details. | F15: Lộc | G15: To Do | H15: iter2 | I15: none | J15: Initial SWP plan: build listing/search/product workflows, approval status handling, database CRUD, and acceptance tests.
... A42: 39 | B42: Support Contact Screen | C42: Post-Booking and Customer Support | D42: Customer, Support Staff | E42: This screen allows Customers to contact Support Staff for help related to booking, payment, refund, ticket, or account issues. It supports the Contact Support use case. | F42: Như | G42: To Do | H42: iter5 | I42: none | J42: Initial SWP plan: build post-booking, refund, review, and support workflows with clear status changes and support-staff handling.
A43: 40 | C43: Post-Booking and Customer Support | E43: This screen allows Attraction Partners to view Customer reviews and respond to them. It supports View Customer Reviews and Respond to Customer Reviews. | F43: Lộc | G43: To Do | H43: iter5 | I43: none | J43: Initial SWP plan: build post-booking, refund, review, and support workflows with clear status changes and support-staff handling.
A44: 41 | B44: Support Request Management Screen | C44: Post-Booking and Customer Support | D44: Support Staff, Customer | E44: This screen allows Support Staff to handle Customer support requests, respond to inquiries, view related booking information, and resolve complaints. It supports Handle Customer Support Request, Respond to Customer Inquiry, View Customer Booking, and Resolve Complaint. | F44: Như | G44: To Do | H44: iter5 | I44: none | J44: Initial SWP plan: build post-booking, refund, review, and support workflows with clear status changes and support-staff handling.
A45: 42 | C45: Post-Booking and Customer Support | E45: This screen allows Support Staff to review refund requests, process approved refunds through the Payment Gateway, and send refund notifications. It supports Process Refund Request, Review Refund Request, Process Refund, and Send Refund Notification. | F45: Lộc | G45: To Do | H45: iter5 | I45: none | J45: Initial SWP plan: build post-booking, refund, review, and support workflows with clear status changes and support-staff handling.
A46: 43 | B46: E-Ticket Reissue Screen | C46: Post-Booking and Customer Support | D46: Support Staff, Customer, Notification Service | E46: This screen allows Support Staff to reissue an e-ticket or QR code when the Customer does not receive the ticket or needs it resent. It supports Reissue E-Ticket and Send E-Ticket Notification. | F46: Như | G46: To Do | H46: iter5 | I46: none | J46: Initial SWP plan: build post-booking, refund, review, and support workflows with clear status changes and support-staff handling.
A47: 44 | B47: Review Moderation Screen | C47: Post-Booking and Customer Support | D47: Admin | E47: This screen allows Admins to moderate Customer reviews and hide reviews that violate platform rules. It supports Moderate Customer Review and Hide Violating Review. | F47: Trần Hoàng Anh | G47: To Do | H47: iter5 | I47: none | J47: Initial SWP plan: build post-booking, refund, review, and support workflows with clear status changes and support-staff handling.
A48: 45 | B48: Partner Booking List Screen | C48: Admin Back-Office and Reporting | D48: Attraction Partner | E48: This screen allows Attraction Partners to view Customer bookings related to their attractions or ticket products. It supports the View Customer Bookings use case. | F48: Lộc | G48: To Do | H48: iter5 | I48: none | J48: Initial SWP plan: build admin reports, voucher/commission configuration, revenue tracking, and dashboard acceptance criteria.
A49: 46 | B49: Partner Revenue Report Screen | C49: Admin Back-Office and Reporting | D49: Attraction Partner | E49: This screen allows Attraction Partners to view revenue reports for ticket sales. It supports the View Revenue Report use case. | F49: Phú | G49: To Do | H49: iter5 | I49: none | J49: Initial SWP plan: build admin reports, voucher/commission configuration, revenue tracking, and dashboard acceptance criteria.
A50: 47 | B50: Payment Tracking Screen | C50: Admin Back-Office and Reporting | D50: Support Staff, Payment Gateway | E50: This screen allows Support Staff to track payment status for bookings, such as paid, failed, pending, or refunded. It supports the Track Payment Status use case. | F50: Phú | G50: To Do | H50: iter5 | I50: none | J50: Initial SWP plan: build admin reports, voucher/commission configuration, revenue tracking, and dashboard acceptance criteria.
A51: 48 | B51: Voucher Management Screen | C51: Admin Back-Office and Reporting | D51: Admin | E51: This screen allows Admins to configure vouchers, create new vouchers, update voucher information, and disable vouchers. It supports Configure Voucher, Create Voucher, Update Voucher, and Disable Voucher. | F51: Trần Hoàng Anh | G51: To Do | H51: iter5 | I51: none | J51: Initial SWP plan: build admin reports, voucher/commission configuration, revenue tracking, and dashboard acceptance criteria.
A52: 49 | B52: Commission Rate Setting Screen | C52: Admin Back-Office and Reporting | D52: Admin | E52: This screen allows Admins to configure the commission rate between the platform and Attraction Partners. It supports the Configure Commission Rate use case. | F52: Trần Hoàng Anh | G52: To Do | H52: iter5 | I52: none | J52: Initial SWP plan: build admin reports, voucher/commission configuration, revenue tracking, and dashboard acceptance criteria.
A53: 50 | B53: Platform Report Dashboard | C53: Admin Back-Office and Reporting | D53: Admin | E53: This screen allows Admins to view platform reports, booking statistics, revenue dashboard, and transaction history. It supports View Platform Reports, View Booking Statistics, View Revenue Dashboard, and View Transaction History. | F53: Phú | G53: To Do | H53: iter5 | I53: none | J53: Initial SWP plan: build admin reports, voucher/commission configuration, revenue tracking, and dashboard acceptance criteria.

Sheet Lists
A1: Status | B1: Iteration | C1: Team Member | D1: Feature | E1: Source
A2: To Do | B2: iter1 | C2: Trần Hoàng Anh | D2: Authentication and Profile Management | E2: project_tracking.docx
A3: Doing | B3: iter2 | C3: Phú | D3: Attraction and Ticket Product Management
A4: Done | B4: iter3 | C4: Lộc | D4: Booking and Payment Management
A5: Updated | B5: iter4 | C5: Như | D5: AI Travel Assistant
A6: Blocked | B6: iter5 | D6: Ticket Validation and Gate Control
B7: none | D7: Post-Booking and Customer Support
D8: Admin Back-Office and Reporting

Sheet Dashboard
A1: Project Tracking Dashboard - Travel Attraction Ticket Booking Platform
A2: Source: project_tracking.docx + Excel template form. Main data table: Project Tracking!A3:J53
A4: KPI | B4: Value | D4: Status | E4: Count | G4: Iteration | H4: Count
A5: Total screens/functions | B5: =COUNTA('Project Tracking'!B4:B53) -> 50 | D5: To Do | E5: =COUNTIF('Project Tracking'!G4:G53,"To Do") -> 50 | G5: iter1 | H5: =COUNTIF('Project Tracking'!H4:H53,"iter1") -> 10
A6: Total features | B6: =COUNTA(Lists!D2:D8) -> 7 | D6: Doing | E6: =COUNTIF('Project Tracking'!G4:G53,"Doing") -> 0 | G6: iter2 | H6: =COUNTIF('Project Tracking'!H4:H53,"iter2") -> 9
A7: Assigned team members | B7: =COUNTA(Lists!C2:C5) -> 4 | D7: Done | E7: =COUNTIF('Project Tracking'!G4:G53,"Done") -> 0 | G7: iter3 | H7: =COUNTIF('Project Tracking'!H4:H53,"iter3") -> 4
D8: Updated | E8: =COUNTIF('Project Tracking'!G4:G53,"Updated") -> 0 | G8: iter4 | H8: =COUNTIF('Project Tracking'!H4:H53,"iter4") -> 10
D9: Blocked | E9: =COUNTIF('Project Tracking'!G4:G53,"Blocked") -> 0 | G9: iter5 | H9: =COUNTIF('Project Tracking'!H4:H53,"iter5") -> 17
A11: Feature Summary | H11: Team Workload
A12: Feature | B12: Total | C12: To Do | D12: Doing | E12: Done/Updated | F12: Blocked | H12: Team Member | I12: Items | J12: Share
A13: Authentication and Profile Management | B13: =COUNTIF('Project Tracking'!$C$4:$C$53,A13) -> 10 | C13: =COUNTIFS('Project Tracking'!$C$4:$C$53,A13,'Project Tracking'!$G$4:$G$53,"To Do") -> 10 | D13: =COUNTIFS('Project Tracking'!$C$4:$C$53,A13,'Project Tracking'!$G$4:$G$53,"Doing") -> 0 | E13: =COUNTIFS('Project Tracking'!$C$4:$C$53,A13,'Project Tracking'!$G$4:$G$53,"Done")+COUNTIFS('Project Tracking'!$C$4:$C$53,A13,'Project Tracking'!$G$4:$G$53,"Updated") -> 0 | F13: =COUNTIFS('Project Tracking'!$C$4:$C$53,A13,'Project Tracking'!$G$4:$G$53,"Blocked") -> 0 | H13: Trần Hoàng Anh | I13: =COUNTIF('Project Tracking'!$F$4:$F$53,H13) -> 10 | J13: =IFERROR(I13/$B$5,0) -> 0.2
A14: Attraction and Ticket Product Management | B14: =COUNTIF('Project Tracking'!$C$4:$C$53,A14) -> 9 | C14: =COUNTIFS('Project Tracking'!$C$4:$C$53,A14,'Project Tracking'!$G$4:$G$53,"To Do") -> 9 | D14: =COUNTIFS('Project Tracking'!$C$4:$C$53,A14,'Project Tracking'!$G$4:$G$53,"Doing") -> 0 | E14: =COUNTIFS('Project Tracking'!$C$4:$C$53,A14,'Project Tracking'!$G$4:$G$53,"Done")+COUNTIFS('Project Tracking'!$C$4:$C$53,A14,'Project Tracking'!$G$4:$G$53,"Updated") -> 0 | F14: =COUNTIFS('Project Tracking'!$C$4:$C$53,A14,'Project Tracking'!$G$4:$G$53,"Blocked") -> 0 | H14: Phú | I14: =COUNTIF('Project Tracking'!$F$4:$F$53,H14) -> 13 | J14: =IFERROR(I14/$B$5,0) -> 0.26
A15: Booking and Payment Management | B15: =COUNTIF('Project Tracking'!$C$4:$C$53,A15) -> 4 | C15: =COUNTIFS('Project Tracking'!$C$4:$C$53,A15,'Project Tracking'!$G$4:$G$53,"To Do") -> 4 | D15: =COUNTIFS('Project Tracking'!$C$4:$C$53,A15,'Project Tracking'!$G$4:$G$53,"Doing") -> 0 | E15: =COUNTIFS('Project Tracking'!$C$4:$C$53,A15,'Project Tracking'!$G$4:$G$53,"Done")+COUNTIFS('Project Tracking'!$C$4:$C$53,A15,'Project Tracking'!$G$4:$G$53,"Updated") -> 0 | F15: =COUNTIFS('Project Tracking'!$C$4:$C$53,A15,'Project Tracking'!$G$4:$G$53,"Blocked") -> 0 | H15: Lộc | I15: =COUNTIF('Project Tracking'!$F$4:$F$53,H15) -> 14 | J15: =IFERROR(I15/$B$5,0) -> 0.28
A16: AI Travel Assistant | B16: =COUNTIF('Project Tracking'!$C$4:$C$53,A16) -> 5 | C16: =COUNTIFS('Project Tracking'!$C$4:$C$53,A16,'Project Tracking'!$G$4:$G$53,"To Do") -> 5 | D16: =COUNTIFS('Project Tracking'!$C$4:$C$53,A16,'Project Tracking'!$G$4:$G$53,"Doing") -> 0 | E16: =COUNTIFS('Project Tracking'!$C$4:$C$53,A16,'Project Tracking'!$G$4:$G$53,"Done")+COUNTIFS('Project Tracking'!$C$4:$C$53,A16,'Project Tracking'!$G$4:$G$53,"Updated") -> 0 | F16: =COUNTIFS('Project Tracking'!$C$4:$C$53,A16,'Project Tracking'!$G$4:$G$53,"Blocked") -> 0 | H16: Như | I16: =COUNTIF('Project Tracking'!$F$4:$F$53,H16) -> 13 | J16: =IFERROR(I16/$B$5,0) -> 0.26
A17: Ticket Validation and Gate Control | B17: =COUNTIF('Project Tracking'!$C$4:$C$53,A17) -> 5 | C17: =COUNTIFS('Project Tracking'!$C$4:$C$53,A17,'Project Tracking'!$G$4:$G$53,"To Do") -> 5 | D17: =COUNTIFS('Project Tracking'!$C$4:$C$53,A17,'Project Tracking'!$G$4:$G$53,"Doing") -> 0 | E17: =COUNTIFS('Project Tracking'!$C$4:$C$53,A17,'Project Tracking'!$G$4:$G$53,"Done")+COUNTIFS('Project Tracking'!$C$4:$C$53,A17,'Project Tracking'!$G$4:$G$53,"Updated") -> 0 | F17: =COUNTIFS('Project Tracking'!$C$4:$C$53,A17,'Project Tracking'!$G$4:$G$53,"Blocked") -> 0
A18: Post-Booking and Customer Support | B18: =COUNTIF('Project Tracking'!$C$4:$C$53,A18) -> 11 | C18: =COUNTIFS('Project Tracking'!$C$4:$C$53,A18,'Project Tracking'!$G$4:$G$53,"To Do") -> 11 | D18: =COUNTIFS('Project Tracking'!$C$4:$C$53,A18,'Project Tracking'!$G$4:$G$53,"Doing") -> 0 | E18: =COUNTIFS('Project Tracking'!$C$4:$C$53,A18,'Project Tracking'!$G$4:$G$53,"Done")+COUNTIFS('Project Tracking'!$C$4:$C$53,A18,'Project Tracking'!$G$4:$G$53,"Updated") -> 0 | F18: =COUNTIFS('Project Tracking'!$C$4:$C$53,A18,'Project Tracking'!$G$4:$G$53,"Blocked") -> 0
A19: Admin Back-Office and Reporting | B19: =COUNTIF('Project Tracking'!$C$4:$C$53,A19) -> 6 | C19: =COUNTIFS('Project Tracking'!$C$4:$C$53,A19,'Project Tracking'!$G$4:$G$53,"To Do") -> 6 | D19: =COUNTIFS('Project Tracking'!$C$4:$C$53,A19,'Project Tracking'!$G$4:$G$53,"Doing") -> 0 | E19: =COUNTIFS('Project Tracking'!$C$4:$C$53,A19,'Project Tracking'!$G$4:$G$53,"Done")+COUNTIFS('Project Tracking'!$C$4:$C$53,A19,'Project Tracking'!$G$4:$G$53,"Updated") -> 0 | F19: =COUNTIFS('Project Tracking'!$C$4:$C$53,A19,'Project Tracking'!$G$4:$G$53,"Blocked") -> 0
